{
  "id": "empty-scene-state",
  "class": "scene-state",
  "purpose": "Catch short scene-setting lines that name a place or scene element and assign an empty state without action, cause, or concrete detail.",
  "matchMode": "contains",
  "templates": [
    "{placeSubject} {linkingVerb} {thinState}.",
    "{placeSubject} {linkingVerb} {thinState} {weakModifier}.",
    "{placeSubject} {linkingVerb} {weakBeforeState} {thinState}.",
    "{placeSubject} went {thinState}.",
    "{sceneElement} {linkingVerb} {thinState}.",
    "{sceneElement} {linkingVerb} {thinState} {weakModifier}.",
    "{sceneElement} {linkingVerb} {weakBeforeState} {thinState}."
  ],
  "slots": {
    "placeSubject": [
      "the room",
      "the yard",
      "the house",
      "the hallway",
      "the kitchen",
      "the office",
      "the classroom",
      "the street",
      "the porch",
      "the table",
      "the stairwell",
      "the lobby",
      "the corridor",
      "the bedroom",
      "the car",
      "the bus stop",
      "the platform",
      "the meeting room",
      "the waiting room",
      "the doorway",
      "the apartment",
      "the studio",
      "the rooms",
      "everything"
    ],
    "sceneElement": [
      "the air",
      "the silence",
      "the space",
      "the light",
      "the morning",
      "the afternoon",
      "the evening",
      "the moment",
      "the room",
      "the scene",
      "the atmosphere",
      "the quiet"
    ],
    "linkingVerb": [
      "was",
      "were",
      "felt",
      "seemed",
      "looked",
      "remained",
      "stayed",
      "became",
      "turned"
    ],
    "thinState": [
      "empty",
      "quiet",
      "still",
      "silent",
      "heavy",
      "cold",
      "dark",
      "dim",
      "hushed",
      "bare",
      "blank",
      "calm",
      "tense",
      "strange",
      "different",
      "unchanged",
      "small",
      "distant"
    ],
    "weakBeforeState": ["just", "suddenly", "so"],
    "weakModifier": ["again", "now", "somehow", "for once", "after that"]
  },
  "rejectIf": [
    "sentence has a cause clause",
    "sentence has a purpose clause",
    "sentence has a concrete sound, object, measurement, name, date, or event detail",
    "thin state is followed by a concrete explanation"
  ],
  "positiveExamples": [
    "The yard was empty.",
    "The room was quiet.",
    "The house felt still.",
    "The air felt heavy.",
    "The hallway stayed silent.",
    "The moment was strange.",
    "The yard went quiet.",
    "The rooms were just empty.",
    "The air felt different now."
  ],
  "negativeExamples": [
    "The yard was empty because the evacuation order had cleared the neighborhood.",
    "The room was quiet enough for the audio recording to capture the fan noise.",
    "The house felt still after the compressor shut off.",
    "The hallway was empty except for two wet umbrellas by the elevator.",
    "The rooms were empty after the movers finished the apartment inventory."
  ],
  "notes": [
    "High precision depends on short sentence length and rejection gates.",
    "Fiction can use this legitimately, so active rule severity must be decided later."
  ]
}
